ssjson/__init__.py
ssjson/ssjson.py
ssjson-1.0.15.dist-info/METADATA
ssjson-1.0.15.dist-info/WHEEL
ssjson-1.0.15.dist-info/top_level.txt
ssjson-1.0.15.dist-info/RECORD
